[1,0,0,[["cc.JsonAsset",["_name","json"],1]],[[0,0,1,3]],[[0,"quest",[{"id":0,"item_id":"product_plant_00","quantity":10,"rewards":[{"quantity":10,"currencyType":"cash"},{"quantity":5000,"currencyType":"gold"}]},{"id":1,"item_id":"product_plant_01","quantity":10,"rewards":[{"quantity":20,"currencyType":"cash"},{"quantity":10000,"currencyType":"gold"}]},{"id":2,"item_id":"product_plant_02","quantity":5,"rewards":[{"quantity":550,"currencyType":"cash"},{"quantity":15000,"currencyType":"gold"}]},{"id":3,"item_id":"product_plant_03","quantity":5,"rewards":[{"quantity":1700,"currencyType":"cash"},{"quantity":20000,"currencyType":"gold"}]},{"id":4,"item_id":"product_plant_04","quantity":5,"rewards":[{"quantity":3500,"currencyType":"cash"},{"quantity":30000,"currencyType":"gold"}]}]]],0,0,[],[],[]]
