[1,0,0,[["cc.JsonAsset",["_name","json"],1]],[[0,0,1,3]],[[0,"shop_item",[{"id":"plant_00","price":1500,"currencyType":"gold","storageTab":"tab_plant"},{"id":"plant_01","price":1500,"currencyType":"gold","storageTab":"tab_plant"},{"id":"plant_02","price":500,"currencyType":"cash","storageTab":"tab_plant"},{"id":"plant_03","price":1500,"currencyType":"cash","storageTab":"tab_plant"},{"id":"plant_04","price":3000,"currencyType":"cash","storageTab":"tab_plant"},{"id":"fertilizer_00","price":3000,"currencyType":"gold","storageTab":"tab_fertilizer"},{"id":"fertilizer_01","price":3000,"currencyType":"cash","storageTab":"tab_fertilizer"},{"id":"water","price":100,"currencyType":"gold","storageTab":"tab_fertilizer"},{"id":"pesticides","price":500,"currencyType":"gold","storageTab":"tab_fertilizer"}]]],0,0,[],[],[]]
